ngwcontractbacktest/__init__.py
ngwcontractbacktest/ngw/__init__.py
ngwcontractbacktest/ngw/constants.py
ngwcontractbacktest/ngw/app_api/__init__.py
ngwcontractbacktest/ngw/app_api/common.py
ngwcontractbacktest/ngw/app_api/execee.py
ngwcontractbacktest/ngw/app_api/trade_api.py
ngwcontractbacktest/ngw/conn_sql/__init__.py
ngwcontractbacktest/ngw/conn_sql/conn_redis.py
ngwcontractbacktest/ngw/conn_sql/insert_sql.py
ngwcontractbacktest/ngw/conn_sql/select_sql.py
ngwcontractbacktest/ngw/context/__init__.py
ngwcontractbacktest/ngw/context/context.py
ngwcontractbacktest/ngw/data/__init__.py
ngwcontractbacktest/ngw/data/cache.py
ngwcontractbacktest/ngw/data/data_api.py
ngwcontractbacktest/ngw/report/__init__.py
ngwcontractbacktest/ngw/report/risk_metrics.py
ngwcontractbacktest/ngw/strategy/__init__.py
ngwcontractbacktest/ngw/strategy/strategy.py
ngwcontractbacktest/ngw/utils/__init__.py
ngwcontractbacktest/ngw/utils/date_util.py
ngwcontractbacktest/ngw/utils/exceptions.py
ngwcontractbacktest/ngw/utils/freq_util.py
ngwcontractbacktest/ngw/utils/log_util.py
ngwcontractbacktest/ngw/utils/print_util.py
ngwcontractbacktest/ngw/utils/thread_util.py
ngwcontractbacktest/ngw/utils/trade_time_util.py
ngwcontractbacktest/ngw/websocket/__init__.py
ngwcontractbacktest/ngw/websocket/websocketClient.py
ngwcontractbacktest-0.1.2.dist-info/METADATA
ngwcontractbacktest-0.1.2.dist-info/WHEEL
ngwcontractbacktest-0.1.2.dist-info/top_level.txt
ngwcontractbacktest-0.1.2.dist-info/RECORD
