Metadata-Version: 2.1
Name: ngwcontractbacktest
Version: 0.1.2
Summary: contract framework 012
Home-page: https://github.com/296348304/ngwcontractbacktest
Author: Wang Jian
Author-email: 296348304@qq.com
License: UNKNOWN
Platform: UNKNOWN
Classifier: Programming Language :: Python :: 3
Classifier: License :: OSI Approved :: MIT License
Classifier: Operating System :: OS Independent
Requires-Python: >=3.7
